pynqc/__init__.py
pynqc/nqc.py
pynqc/raw_functions.py
pynqc-0.1.dist-info/LICENSE
pynqc-0.1.dist-info/METADATA
pynqc-0.1.dist-info/WHEEL
pynqc-0.1.dist-info/top_level.txt
pynqc-0.1.dist-info/RECORD
