Metadata-Version: 2.1
Name: pynqc
Version: 0.1
Summary: Wrapper for the nqc executable
Home-page: https://gitlab.com/solsjo/pynqc
Author: Oskar Solsjö
Author-email: oskar.solsjo@gmail.com
License: MIT
Platform: UNKNOWN
Classifier: Programming Language :: Python :: 3.6
Classifier: Programming Language :: Python :: 3.7
Classifier: Programming Language :: Python :: 3.8
Classifier: Operating System :: POSIX :: Linux
Requires-Python: >=3.6
